{
  "name": "MathOptFormat Model",
  "version": {
    "major": 1,
    "minor": 4
  },
  "variables": [
    {
      "name": "x_in"
    },
    {
      "name": "ξ"
    },
    {
      "name": "x_out"
    },
    {
      "name": "y"
    },
    {
      "name": "x5"
    },
    {
      "name": "x6"
    }
  ],
  "objective": {
    "sense": "min",
    "function": {
      "type": "ScalarAffineFunction",
      "terms": [
        {
          "coefficient": 1.0,
          "variable": "y"
        },
        {
          "coefficient": 1.0,
          "variable": "x_out"
        },
        {
          "coefficient": 1.0,
          "variable": "x6"
        }
      ],
      "constant": 0.0
    }
  },
  "constraints": [
    {
      "name": "c1",
      "function": {
        "type": "ScalarAffineFunction",
        "terms": [
          {
            "coefficient": 1.0,
            "variable": "x_in"
          },
          {
            "coefficient": -1.0,
            "variable": "ξ"
          },
          {
            "coefficient": -1.0,
            "variable": "x_out"
          },
          {
            "coefficient": 1.0,
            "variable": "y"
          }
        ],
        "constant": 0.0
      },
      "set": {
        "type": "EqualTo",
        "value": 0.0
      }
    },
    {
      "name": "ubound",
      "function": {
        "type": "ScalarAffineFunction",
        "terms": [
          {
            "coefficient": 1.0,
            "variable": "x_out"
          }
        ],
        "constant": 0.0
      },
      "set": {
        "type": "LessThan",
        "upper": 6.0
      }
    },
    {
      "name": "c2",
      "function": {
        "type": "ScalarAffineFunction",
        "terms": [
          {
            "coefficient": 1.0,
            "variable": "y"
          }
        ],
        "constant": 0.0
      },
      "set": {
        "type": "LessThan",
        "upper": 6.0
      }
    },
    {
      "function": {
        "type": "Variable",
        "name": "x_in"
      },
      "set": {
        "type": "EqualTo",
        "value": 0.42253992568406584
      }
    },
    {
      "function": {
        "type": "Variable",
        "name": "ξ"
      },
      "set": {
        "type": "EqualTo",
        "value": 18.3931738294204
      }
    },
    {
      "function": {
        "type": "Variable",
        "name": "x_out"
      },
      "set": {
        "type": "GreaterThan",
        "lower": 0.0
      }
    },
    {
      "function": {
        "type": "Variable",
        "name": "y"
      },
      "set": {
        "type": "GreaterThan",
        "lower": 0.0
      }
    },
    {
      "function": {
        "type": "Variable",
        "name": "x5"
      },
      "set": {
        "type": "GreaterThan",
        "lower": 0.0
      }
    },
    {
      "function": {
        "type": "Variable",
        "name": "x6"
      },
      "set": {
        "type": "GreaterThan",
        "lower": 0.0
      }
    },
    {
      "function": {
        "type": "Variable",
        "name": "x5"
      },
      "set": {
        "type": "LessThan",
        "upper": 0.0
      }
    },
    {
      "function": {
        "type": "Variable",
        "name": "x6"
      },
      "set": {
        "type": "LessThan",
        "upper": 0.0
      }
    }
  ]
}
